{
  "baseLayers": [
    {
      "id": 0,
      "title": "Roads",
      "type": "OSM",
      "source": {
        "url": "http://{a-c}.tile.openstreetmap.org/{z}/{x}/{y}.png",
        "attribution": "(c) OpenStreetMap contributers"
      },
      "visible": true
    },
    {
      "id": 1,
      "title": "Cycling Map",
      "type": "OSM",
      "source": {
        "url": "http://{a-c}.tile.opencyclemap.org/cycle/{z}/{x}/{y}.png",
        "attribution": "(c) OpenCycleMap and OpenStreetMap contributors"
      }
    }
  ],
  "featureLayers": [
    {
      "id": 2,
      "title": "Hotels in Bonn",
      "type": "KML",
      "source": {
        "url": "files/hotelsbonn.kml",
        "attribution": "(c) OpenStreetMap contributers"
      }
    },
    {
      "id": 3,
      "title": "Restaurants in Bonn",
      "type": "KML",
      "source": {
        "url": "files/restaurantsbonn.kml",
        "attribution": "(c) OpenStreetMap contributers"
      }
    }
  ]
}